[
    {
        "gspid": "99810",
        "gid": "208638",
        "cateid": "10",
        "subject": "宝路 绿茶口味大型犬成犬洁齿棒 115g",
        "presubject": "含洁牙因子 减少牙垢积累 绿茶辅助清新口气",
        "formats": "",
        "formats_values": "[]",
        "photo": "//img1.epetbar.com/2017-08/30/15/b41961ff7e228e4e566d8575b0c9280f.jpg@!200w-c",
        "sale_price": "15.60",
        "market_price": "19.00",
        "youhui_price": "0.00",
        "fm_shareid": "0",
        "brandid": "47",
        "order": "900",
        "stockmode": "2",
        "replys": "607",
        "asks": "2",
        "net_weight": "120.000",
        "nagpre": "0.04",
        "sold": "4085",
        "unit": "袋",
        "isBest": "1",
        "stock": "1",
        "real_wid": "1",
        "href": "http://item.epet.com/208638.html"
    },
    {
        "gspid": "7346",
        "gid": "107346",
        "cateid": "10",
        "subject": "宝路 幼犬钙奶棒 60g ",
        "presubject": "经典爆款钙奶棒 幼犬磨牙 大包实惠更尽兴",
        "formats": " 单袋装",
        "formats_values": "{\"7487\":9793}",
        "photo": "//img1.epetbar.com/2016-06/27/14/41066cb7508efe00ac51892201b7ea5c.jpg@!200w-c",
        "sale_price": "10.40",
        "market_price": "12.48",
        "youhui_price": "8.55",
        "fm_shareid": "153016",
        "brandid": "47",
        "order": "800",
        "stockmode": "2",
        "replys": "10390",
        "asks": "830",
        "net_weight": "60.000",
        "nagpre": "0.02",
        "sold": "58723",
        "unit": "袋",
        "isBest": "1",
        "stock": "1",
        "real_wid": "1",
        "href": "http://item.epet.com/107346.html"
    },
    {
        "gspid": "31547",
        "gid": "133123",
        "cateid": "10",
        "subject": "蒙贝 自然香酥带肉牛棒骨 L号",
        "presubject": "甄选内蒙肥牛 磨牙/洁齿/补充营养 盒装与简装（无纸盒）随机发",
        "formats": " L",
        "formats_values": "{\"7511\":7633}",
        "photo": "//img1.epetbar.com/2017-08/11/11/874d77c8e14318417e182b8c9ffab4f6.jpg@!200w-c",
        "sale_price": "33.00",
        "market_price": "39.60",
        "youhui_price": "18.00",
        "fm_shareid": "133123",
        "brandid": "330",
        "order": "800",
        "stockmode": "2",
        "replys": "19049",
        "asks": "1351",
        "net_weight": "200.000",
        "nagpre": "0.03",
        "sold": "39409",
        "unit": "支",
        "isBest": "1",
        "stock": "1",
        "real_wid": "1",
        "href": "http://item.epet.com/133123.html"
    },
    {
        "gspid": "32499",
        "gid": "134087",
        "cateid": "10",
        "subject": "蒙贝 6月以上中小型犬 天然小龙骨 6片",
        "presubject": "磨牙健齿 补钙强骨 呵护关节 健康营养",
        "formats": " 单罐装",
        "formats_values": "{\"7487\":10874}",
        "photo": "//img1.epetbar.com/2017-05/04/10/93a0ff47919bb4c78398eb6ad5cca0e7.jpg@!200w-c",
        "sale_price": "26.80",
        "market_price": "32.16",
        "youhui_price": "0.00",
        "fm_shareid": "134087",
        "brandid": "330",
        "order": "800",
        "stockmode": "2",
        "replys": "3037",
        "asks": "50",
        "net_weight": "70.000",
        "nagpre": "0.03",
        "sold": "14984",
        "unit": "罐",
        "isBest": "1",
        "stock": "1",
        "real_wid": "1",
        "href": "http://item.epet.com/134087.html"
    },
    {
        "gspid": "69701",
        "gid": "175935",
        "cateid": "10",
        "subject": "美国原装进口 梅里亚 牙口乐犬用口腔清洁棒 XS 14支/盒 161g",
        "presubject": "物理摩擦 不伤牙龈 改善口臭/牙菌斑/牙结石 4.5kg以下适用 ",
        "formats": " XS 整盒装",
        "formats_values": "{\"7505\":12263,\"7511\":7635}",
        "photo": "//img1.epetbar.com/2017-06/02/8/9155667a8e9c550797b299d1d32c759c.jpg@!200w-c",
        "sale_price": "70.00",
        "market_price": "96.40",
        "youhui_price": "62.40",
        "fm_shareid": "175939",
        "brandid": "1391",
        "order": "800",
        "stockmode": "2",
        "replys": "5054",
        "asks": "77",
        "net_weight": "100.000",
        "nagpre": "0.04",
        "sold": "5334",
        "unit": "盒",
        "isBest": "1",
        "stock": "1",
        "real_wid": "1",
        "href": "http://item.epet.com/175935.html"
    },
    {
        "gspid": "45256",
        "gid": "147300",
        "cateid": "10",
        "subject": "蒙贝 自然香酥带肉牛棒骨 S号 ",
        "presubject": "甄选内蒙肥牛 磨牙/洁齿/添营养 黄绿包装随机发",
        "formats": " S",
        "formats_values": "{\"7511\":7637}",
        "photo": "//img1.epetbar.com/2017-08/11/11/e967fa05468c83df86b3ef375642bdd0.jpg@!200w-c",
        "sale_price": "22.80",
        "market_price": "27.36",
        "youhui_price": "0.00",
        "fm_shareid": "133123",
        "brandid": "330",
        "order": "799",
        "stockmode": "2",
        "replys": "19049",
        "asks": "1351",
        "net_weight": "100.000",
        "nagpre": "0.04",
        "sold": "39723",
        "unit": "支",
        "isBest": "1",
        "stock": "1",
        "real_wid": "1",
        "href": "http://item.epet.com/147300.html"
    },
    {
        "gspid": "17050",
        "gid": "117109",
        "cateid": "10",
        "subject": "蒙贝 自然香酥带肉牛棒骨 M号",
        "presubject": "甄选内蒙肥牛 磨牙/洁齿/添营养 建议3月以上狗狗食用",
        "formats": " M",
        "formats_values": "{\"7511\":7639}",
        "photo": "//img1.epetbar.com/2017-08/11/11/766db093b8e5a65a4dab3bff4ea775d9.jpg@!200w-c",
        "sale_price": "26.80",
        "market_price": "32.16",
        "youhui_price": "0.00",
        "fm_shareid": "133123",
        "brandid": "330",
        "order": "798",
        "stockmode": "2",
        "replys": "19049",
        "asks": "1351",
        "net_weight": "150.000",
        "nagpre": "0.03",
        "sold": "28022",
        "unit": "支",
        "isBest": "1",
        "stock": "1",
        "real_wid": "1",
        "href": "http://item.epet.com/117109.html"
    },
    {
        "gspid": "109353",
        "gid": "218987",
        "cateid": "10",
        "subject": "蒙贝 手抓牛排狗零食 80g",
        "presubject": "源自蒙古大草原 牛肉裹牛胫骨 美味磨牙",
        "formats": "",
        "formats_values": "[]",
        "photo": "//img1.epetbar.com/2017-09/19/11/39b8990aa0b7248d291a016c9312a998.jpg@!200w-c",
        "sale_price": "14.80",
        "market_price": "17.76",
        "youhui_price": "0.00",
        "fm_shareid": "0",
        "brandid": "330",
        "order": "798",
        "stockmode": "2",
        "replys": "170",
        "asks": "0",
        "net_weight": "0.000",
        "nagpre": "0.02",
        "sold": "817",
        "unit": "盒",
        "isBest": "1",
        "stock": "1",
        "real_wid": "1",
        "href": "http://item.epet.com/218987.html"
    },
    {
        "gspid": "131249",
        "gid": "237839",
        "cateid": "132",
        "subject": "禾仕嘉 烘焙嫩羊狗零食 200g",
        "presubject": "科学配比 自然肉香 多种营养 易消化吸收 ",
        "formats": " 烘焙嫩羊",
        "formats_values": "{\"7515\":17804}",
        "photo": "//img1.epetbar.com/2018-03/30/09/8d0ff6fe8e2c6f1368006534686488ed.png@!200w-c",
        "sale_price": "29.00",
        "market_price": "35.00",
        "youhui_price": "0.00",
        "fm_shareid": "237839",
        "brandid": "182",
        "order": "900",
        "stockmode": "2",
        "replys": "394",
        "asks": "0",
        "net_weight": "200.000",
        "nagpre": "0.02",
        "sold": "164",
        "unit": "袋",
        "isBest": "1",
        "stock": "1",
        "real_wid": "1",
        "href": "http://item.epet.com/237839.html"
    },
    {
        "gspid": "12689",
        "gid": "112689",
        "cateid": "132",
        "subject": "爱丽思IRIS 鸡胸肉硬切片 160g ",
        "presubject": "天然食材 蛋白质丰富 更适合磨牙 ",
        "formats": " 鸡胸肉硬片",
        "formats_values": "{\"7515\":18273}",
        "photo": "//img1.epetbar.com/2016-10/17/8/87dedbb22bfd08ac81e7ce848cb816a4.jpg@!200w-c",
        "sale_price": "19.00",
        "market_price": "38.00",
        "youhui_price": "0.00",
        "fm_shareid": "118267",
        "brandid": "30",
        "order": "800",
        "stockmode": "2",
        "replys": "5554",
        "asks": "27",
        "net_weight": "160.000",
        "nagpre": "0.02",
        "sold": "8118",
        "unit": "袋",
        "isBest": "1",
        "stock": "1",
        "real_wid": "1",
        "href": "http://item.epet.com/112689.html"
    },
    {
        "gspid": "18206",
        "gid": "118267",
        "cateid": "132",
        "subject": "爱丽思IRIS 烘干鸡胸肉干 160g",
        "presubject": "无色素 无添加 蛋白质丰富",
        "formats": " 鸡胸肉干",
        "formats_values": "{\"7515\":11945}",
        "photo": "//img1.epetbar.com/2014-12/05/724b911854c267e53783515c89c181c4.jpg@!200w-c",
        "sale_price": "19.00",
        "market_price": "38.00",
        "youhui_price": "0.00",
        "fm_shareid": "118267",
        "brandid": "30",
        "order": "800",
        "stockmode": "2",
        "replys": "5554",
        "asks": "47",
        "net_weight": "160.000",
        "nagpre": "0.02",
        "sold": "16668",
        "unit": "袋",
        "isBest": "1",
        "stock": "1",
        "real_wid": "1",
        "href": "http://item.epet.com/118267.html"
    },
    {
        "gspid": "31325",
        "gid": "132901",
        "cateid": "132",
        "subject": "路斯 手工坊系列 高钙牛肉段 200g ",
        "presubject": "越嚼越香 营养低脂 训练奖励 ",
        "formats": "",
        "formats_values": "[]",
        "photo": "//img1.epetbar.com/2016-03/25/16/267f57bfdd34167fd4d993d8d6d21afb.jpg@!200w-c",
        "sale_price": "13.80",
        "market_price": "18.00",
        "youhui_price": "0.00",
        "fm_shareid": "0",
        "brandid": "318",
        "order": "800",
        "stockmode": "2",
        "replys": "1748",
        "asks": "20",
        "net_weight": "200.000",
        "nagpre": "0.02",
        "sold": "9970",
        "unit": "包",
        "isBest": "1",
        "stock": "1",
        "real_wid": "1",
        "href": "http://item.epet.com/132901.html"
    },
    {
        "gspid": "52547",
        "gid": "154976",
        "cateid": "132",
        "subject": "顽皮Wanpy 醇香牛肉棒 400g ",
        "presubject": "精选牛肉 18道工序加工 低温风干 原质原味 醇香美味",
        "formats": "",
        "formats_values": "[]",
        "photo": "//img1.epetbar.com/2017-09/27/09/1728b057162ddbebf7b32cbaca7912b2.jpg@!200w-c",
        "sale_price": "16.80",
        "market_price": "20.16",
        "youhui_price": "0.00",
        "fm_shareid": "0",
        "brandid": "122",
        "order": "800",
        "stockmode": "2",
        "replys": "16394",
        "asks": "68",
        "net_weight": "500.000",
        "nagpre": "0.02",
        "sold": "73714",
        "unit": "袋",
        "isBest": "1",
        "stock": "1",
        "real_wid": "1",
        "href": "http://item.epet.com/154976.html"
    },
    {
        "gspid": "93473",
        "gid": "201665",
        "cateid": "132",
        "subject": "顽皮Wanpy 犬用香脆牛肝片180g",
        "presubject": "可溯源牛肝 好吃耐嚼 醇香十足 低温风干 原质原味",
        "formats": "",
        "formats_values": "[]",
        "photo": "//img1.epetbar.com/2018-07/12/13/47eea6973ac24029b2628fc14029d190.jpg@!200w-c",
        "sale_price": "19.90",
        "market_price": "35.88",
        "youhui_price": "0.00",
        "fm_shareid": "201665",
        "brandid": "122",
        "order": "800",
        "stockmode": "2",
        "replys": "1642",
        "asks": "2",
        "net_weight": "180.000",
        "nagpre": "0.03",
        "sold": "7225",
        "unit": "罐",
        "isBest": "1",
        "stock": "1",
        "real_wid": "1",
        "href": "http://item.epet.com/201665.html"
    },
    {
        "gspid": "131248",
        "gid": "237838",
        "cateid": "132",
        "subject": "禾仕嘉 远洋鲜鱼狗零食 200g",
        "presubject": "科学配比 自然肉香 多种营养 易消化吸收 ",
        "formats": " 远洋鲜鱼",
        "formats_values": "{\"7515\":17803}",
        "photo": "//img1.epetbar.com/2018-03/30/09/94ae6410d1578468833d787611bc7fa8.png@!200w-c",
        "sale_price": "29.00",
        "market_price": "35.00",
        "youhui_price": "0.00",
        "fm_shareid": "237839",
        "brandid": "182",
        "order": "800",
        "stockmode": "2",
        "replys": "394",
        "asks": "0",
        "net_weight": "200.000",
        "nagpre": "0.06",
        "sold": "220",
        "unit": "袋",
        "isBest": "1",
        "stock": "1",
        "real_wid": "1",
        "href": "http://item.epet.com/237838.html"
    },
    {
        "gspid": "53299",
        "gid": "155752",
        "cateid": "132",
        "subject": "蒙贝 牛肉胡萝卜粒 180g",
        "presubject": "肉蔬混搭 营养美味 草原牛肉 强肌健体 ",
        "formats": " 牛肉胡萝卜粒",
        "formats_values": "{\"7515\":10841}",
        "photo": "//img1.epetbar.com/2018-12/29/14/79d425eb14d3ec0416f76f3bb27ff098.jpg@!200w-c",
        "sale_price": "25.80",
        "market_price": "30.96",
        "youhui_price": "0.00",
        "fm_shareid": "155751",
        "brandid": "330",
        "order": "791",
        "stockmode": "2",
        "replys": "4763",
        "asks": "74",
        "net_weight": "180.000",
        "nagpre": "0.02",
        "sold": "4487",
        "unit": "罐",
        "isBest": "1",
        "stock": "1",
        "real_wid": "1",
        "href": "http://item.epet.com/155752.html"
    },
    {
        "gspid": "127038",
        "gid": "233235",
        "cateid": "133",
        "subject": "蒙贝 犬用酪咔奶条 原味 120g",
        "presubject": "高钙易吸收 增强骨骼发育",
        "formats": " 原味",
        "formats_values": "{\"7515\":8955}",
        "photo": "//img1.epetbar.com/2018-01/24/09/9d25c53fd854c1f83a1b4527d02ae3f2.jpg@!200w-c",
        "sale_price": "24.80",
        "market_price": "29.76",
        "youhui_price": "0.00",
        "fm_shareid": "233235",
        "brandid": "330",
        "order": "795",
        "stockmode": "2",
        "replys": "518",
        "asks": "0",
        "net_weight": "70.000",
        "nagpre": "0.03",
        "sold": "892",
        "unit": "袋",
        "isBest": "1",
        "stock": "1",
        "real_wid": "1",
        "href": "http://item.epet.com/233235.html"
    },
    {
        "gspid": "127039",
        "gid": "233236",
        "cateid": "133",
        "subject": "蒙贝 犬用酪咔奶条 蓝莓味 120g",
        "presubject": "高钙易吸收 增强视力 保护眼睛",
        "formats": " 蓝莓味",
        "formats_values": "{\"7515\":10294}",
        "photo": "//img1.epetbar.com/2018-01/24/09/338e42876ee855927fbbf90cb7b3a1c1.jpg@!200w-c",
        "sale_price": "24.80",
        "market_price": "29.76",
        "youhui_price": "0.00",
        "fm_shareid": "233235",
        "brandid": "330",
        "order": "794",
        "stockmode": "2",
        "replys": "518",
        "asks": "0",
        "net_weight": "70.000",
        "nagpre": "0.04",
        "sold": "416",
        "unit": "袋",
        "isBest": "1",
        "stock": "1",
        "real_wid": "1",
        "href": "http://item.epet.com/233236.html"
    },
    {
        "gspid": "127040",
        "gid": "233237",
        "cateid": "133",
        "subject": "蒙贝 犬用酪咔奶条 蔓越莓味 120g",
        "presubject": "高钙易吸收 美毛亮毛 保护肠胃",
        "formats": " 蔓越莓味",
        "formats_values": "{\"7515\":17361}",
        "photo": "//img1.epetbar.com/2018-01/24/09/e0163627938fd57b90d1d1762275c027.jpg@!200w-c",
        "sale_price": "24.80",
        "market_price": "29.76",
        "youhui_price": "0.00",
        "fm_shareid": "233235",
        "brandid": "330",
        "order": "793",
        "stockmode": "2",
        "replys": "518",
        "asks": "0",
        "net_weight": "70.000",
        "nagpre": "0.03",
        "sold": "1035",
        "unit": "袋",
        "isBest": "1",
        "stock": "1",
        "real_wid": "1",
        "href": "http://item.epet.com/233237.html"
    },
    {
        "gspid": "109355",
        "gid": "218989",
        "cateid": "133",
        "subject": "蒙贝 酪咔奶酪狗零食 120g",
        "presubject": "口感丝滑 味道醇香 添加益生菌和DHA 补钙护肠",
        "formats": "",
        "formats_values": "[]",
        "photo": "//img1.epetbar.com/2017-09/19/11/f0e4f6f155dbb01b031dcb9c8a7efe03.jpg@!200w-c",
        "sale_price": "21.80",
        "market_price": "26.16",
        "youhui_price": "0.00",
        "fm_shareid": "0",
        "brandid": "330",
        "order": "787",
        "stockmode": "2",
        "replys": "338",
        "asks": "0",
        "net_weight": "0.000",
        "nagpre": "0.03",
        "sold": "1110",
        "unit": "袋",
        "isBest": "1",
        "stock": "1",
        "real_wid": "1",
        "href": "http://item.epet.com/218989.html"
    },
    {
        "gspid": "127044",
        "gid": "233241",
        "cateid": "133",
        "subject": "蒙贝 酪咔汪星奶酪 黑芝麻 120g",
        "presubject": "添加活性益生菌和DHA 高钙易吸收",
        "formats": " 黑芝麻",
        "formats_values": "{\"7515\":17369}",
        "photo": "//img1.epetbar.com/2018-01/24/11/0a17875ea841f333d82d4b1057e126a1.jpg@!200w-c",
        "sale_price": "24.80",
        "market_price": "29.76",
        "youhui_price": "0.00",
        "fm_shareid": "233240",
        "brandid": "330",
        "order": "786",
        "stockmode": "2",
        "replys": "169",
        "asks": "0",
        "net_weight": "120.000",
        "nagpre": "0.03",
        "sold": "384",
        "unit": "袋",
        "isBest": "1",
        "stock": "1",
        "real_wid": "1",
        "href": "http://item.epet.com/233241.html"
    },
    {
        "gspid": "127043",
        "gid": "233240",
        "cateid": "133",
        "subject": "蒙贝 酪咔汪星奶酪 紫薯 120g",
        "presubject": "添加活性益生菌和DHA 高钙易吸收",
        "formats": " 紫薯",
        "formats_values": "{\"7515\":10852}",
        "photo": "//img1.epetbar.com/2018-01/24/11/023b6ce8104b109aedc4e1d4f37d5c7c.jpg@!200w-c",
        "sale_price": "24.80",
        "market_price": "29.76",
        "youhui_price": "0.00",
        "fm_shareid": "233240",
        "brandid": "330",
        "order": "785",
        "stockmode": "2",
        "replys": "169",
        "asks": "0",
        "net_weight": "120.000",
        "nagpre": "0.06",
        "sold": "273",
        "unit": "袋",
        "isBest": "1",
        "stock": "1",
        "real_wid": "1",
        "href": "http://item.epet.com/233240.html"
    },
    {
        "gspid": "116007",
        "gid": "226340",
        "cateid": "133",
        "subject": "蒙贝 酪咔奶泡 160g",
        "presubject": "香脆可口 健齿补钙 无添加剂 低温烘烤",
        "formats": "",
        "formats_values": "",
        "photo": "//img1.epetbar.com/2017-11/24/13/7b6aadb26ac751a6cfeb66e5ad2fac17.jpg@!200w-c",
        "sale_price": "38.00",
        "market_price": "46.00",
        "youhui_price": "0.00",
        "fm_shareid": "0",
        "brandid": "330",
        "order": "783",
        "stockmode": "2",
        "replys": "125",
        "asks": "0",
        "net_weight": "160.000",
        "nagpre": "0.04",
        "sold": "409",
        "unit": "罐",
        "isBest": "1",
        "stock": "1",
        "real_wid": "1",
        "href": "http://item.epet.com/226340.html"
    },
    {
        "gspid": "3564",
        "gid": "103564",
        "cateid": "133",
        "subject": "Hugdarling哈格 脱脂酸奶曲奇棒狗零食 200g",
        "presubject": "香浓美味 洁齿护牙 营养补钙",
        "formats": "",
        "formats_values": "[]",
        "photo": "//img1.epetbar.com/2015-10/16/16/3fec38d26f608a8876cecee339473a1c.jpg@!200w-c",
        "sale_price": "8.80",
        "market_price": "12.00",
        "youhui_price": "0.00",
        "fm_shareid": "103564",
        "brandid": "110",
        "order": "700",
        "stockmode": "2",
        "replys": "2658",
        "asks": "78",
        "net_weight": "0.000",
        "nagpre": "0.03",
        "sold": "12590",
        "unit": "袋",
        "isBest": "1",
        "stock": "1",
        "real_wid": "1",
        "href": "http://item.epet.com/103564.html"
    },
    {
        "gspid": "7348",
        "gid": "107348",
        "cateid": "135",
        "subject": "宝路 成犬 鲜肝妙鲜包 100g ",
        "presubject": "宝路经典妙鲜包 干湿均衡搭配 大包更划算",
        "formats": " 单袋装 鲜肝",
        "formats_values": "{\"7487\":9793,\"7515\":9862}",
        "photo": "//img1.epetbar.com/2016-06/27/10/f6bb3277c853124931de3c9f34c2b1f1.jpg@!200w-c",
        "sale_price": "3.90",
        "market_price": "5.68",
        "youhui_price": "0.00",
        "fm_shareid": "153011",
        "brandid": "47",
        "order": "900",
        "stockmode": "2",
        "replys": "12919",
        "asks": "384",
        "net_weight": "0.000",
        "nagpre": "0.02",
        "sold": "10905",
        "unit": "袋",
        "isBest": "1",
        "stock": "1",
        "real_wid": "1",
        "href": "http://item.epet.com/107348.html"
    },
    {
        "gspid": "50695",
        "gid": "153011",
        "cateid": "135",
        "subject": "宝路 成犬 牛肉妙鲜包 100g*12袋装",
        "presubject": "宝路经典妙鲜包 干湿均衡搭配 大包更划算",
        "formats": " 整盒装 牛肉",
        "formats_values": "{\"7487\":7565,\"7515\":7581}",
        "photo": "//img1.epetbar.com/2016-06/27/12/dd4d6a2f5a9ef11293c028a4bd605c36.jpg@!200w-c",
        "sale_price": "39.90",
        "market_price": "47.88",
        "youhui_price": "0.00",
        "fm_shareid": "153011",
        "brandid": "47",
        "order": "900",
        "stockmode": "2",
        "replys": "12919",
        "asks": "384",
        "net_weight": "1200.000",
        "nagpre": "0.03",
        "sold": "13778",
        "unit": "盒",
        "isBest": "1",
        "stock": "1",
        "real_wid": "1",
        "href": "http://item.epet.com/153011.html"
    },
    {
        "gspid": "116146",
        "gid": "226482",
        "cateid": "135",
        "subject": "新西兰原装进口 爱谛iti 无谷狗罐头 牛肉 175g",
        "presubject": "90%鲜肉 自由放养动物成分 无谷物 无转基因 营养兼美味",
        "formats": " 牛肉",
        "formats_values": "{\"7515\":7581}",
        "photo": "//img1.epetbar.com/2017-12/05/16/9686931fda32ad0776f7fed19a7122ee.jpg@!200w-c",
        "sale_price": "29.00",
        "market_price": "34.00",
        "youhui_price": "0.00",
        "fm_shareid": "226480",
        "brandid": "1946",
        "order": "850",
        "stockmode": "2",
        "replys": "189",
        "asks": "0",
        "net_weight": "180.000",
        "nagpre": "0.00",
        "sold": "520",
        "unit": "罐",
        "isBest": "1",
        "stock": "1",
        "real_wid": "1",
        "href": "http://item.epet.com/226482.html"
    },
    {
        "gspid": "5079",
        "gid": "105079",
        "cateid": "135",
        "subject": "宝路 幼犬鸡肉妙鲜包 85g ",
        "presubject": "营养健康 均衡配比 口感佳",
        "formats": " 鸡肉 单袋装",
        "formats_values": "{\"7487\":9793,\"7515\":7579}",
        "photo": "//img1.epetbar.com/2016-06/27/16/5f13d590e661e2e720e99144e043e9ee.jpg@!200w-c",
        "sale_price": "3.90",
        "market_price": "5.68",
        "youhui_price": "0.00",
        "fm_shareid": "153013",
        "brandid": "47",
        "order": "800",
        "stockmode": "2",
        "replys": "6085",
        "asks": "391",
        "net_weight": "80.000",
        "nagpre": "0.02",
        "sold": "16457",
        "unit": "袋",
        "isBest": "1",
        "stock": "1",
        "real_wid": "1",
        "href": "http://item.epet.com/105079.html"
    },
    {
        "gspid": "14926",
        "gid": "114926",
        "cateid": "135",
        "subject": "爱丽思IRIS 牛肉砂肝 鲜封包 250g 牛肉砂肝",
        "presubject": "天然食材 营养均衡 无添加",
        "formats": " 牛肉砂肝",
        "formats_values": "{\"7515\":10398}",
        "photo": "//img1.epetbar.com/2016-03/23/14/e2e466d5a7c0edc7d8fc4205a77a1c9e.jpg@!200w-c",
        "sale_price": "9.38",
        "market_price": "10.00",
        "youhui_price": "0.00",
        "fm_shareid": "114928",
        "brandid": "30",
        "order": "800",
        "stockmode": "2",
        "replys": "7181",
        "asks": "301",
        "net_weight": "250.000",
        "nagpre": "0.02",
        "sold": "16075",
        "unit": "袋",
        "isBest": "1",
        "stock": "1",
        "real_wid": "1",
        "href": "http://item.epet.com/114926.html"
    },
    {
        "gspid": "50698",
        "gid": "153014",
        "cateid": "135",
        "subject": "宝路 成犬 滑嫩鸡肉妙鲜包 100g*12袋装",
        "presubject": "宝路经典妙鲜包 干湿均衡搭配 大包更划算",
        "formats": " 整盒装 鸡肉",
        "formats_values": "{\"7487\":7565,\"7515\":7579}",
        "photo": "//img1.epetbar.com/2016-06/27/10/b2b372abdd1093dc5d94d0ab82788111.jpg@!200w-c",
        "sale_price": "39.90",
        "market_price": "56.16",
        "youhui_price": "0.00",
        "fm_shareid": "153011",
        "brandid": "47",
        "order": "800",
        "stockmode": "2",
        "replys": "12919",
        "asks": "384",
        "net_weight": "1200.000",
        "nagpre": "0.03",
        "sold": "5679",
        "unit": "盒",
        "isBest": "1",
        "stock": "1",
        "real_wid": "1",
        "href": "http://item.epet.com/153014.html"
    },
    {
        "gspid": "57252",
        "gid": "160840",
        "cateid": "135",
        "subject": "比瑞吉 益生元幼犬奶糕罐头 156g",
        "presubject": "母乳般温和 呵护柔嫩肠胃",
        "formats": "",
        "formats_values": "[]",
        "photo": "//img1.epetbar.com/2018-11/29/18/c4e0f00747b27dc72b9c9de086996e37.jpg@!200w-c",
        "sale_price": "21.00",
        "market_price": "51.00",
        "youhui_price": "0.00",
        "fm_shareid": "160840",
        "brandid": "334",
        "order": "800",
        "stockmode": "2",
        "replys": "1935",
        "asks": "76",
        "net_weight": "160.000",
        "nagpre": "0.03",
        "sold": "10289",
        "unit": "罐",
        "isBest": "1",
        "stock": "1",
        "real_wid": "1",
        "href": "http://item.epet.com/160840.html"
    },
    {
        "gspid": "127589",
        "gid": "233941",
        "cateid": "135",
        "subject": "美国卡比 无谷狗用主食罐 鸡肉+蔬菜 70g",
        "presubject": "泰国生产 鲜肉浓汤 肉片嫩滑 无谷配方 简单成分 低敏易消化",
        "formats": " 鸡肉+蔬菜 70g",
        "formats_values": "{\"7505\":14455,\"7515\":9527}",
        "photo": "//img1.epetbar.com/2018-03/19/11/3816e33f19dc2581b45e4c8d5211c139.jpg@!200w-c",
        "sale_price": "14.00",
        "market_price": "16.80",
        "youhui_price": "0.00",
        "fm_shareid": "233940",
        "brandid": "19",
        "order": "800",
        "stockmode": "2",
        "replys": "1292",
        "asks": "0",
        "net_weight": "70.000",
        "nagpre": "0.03",
        "sold": "645",
        "unit": "罐",
        "isBest": "1",
        "stock": "1",
        "real_wid": "1",
        "href": "http://item.epet.com/233941.html"
    },
    {
        "gspid": "12841",
        "gid": "112841",
        "cateid": "4306",
        "subject": "顽皮Wanpy 奶酪小馒头 220g",
        "presubject": "精心烘焙 口感酥脆 奶香浓郁 营养均衡 补充钙质",
        "formats": "",
        "formats_values": "[]",
        "photo": "//img1.epetbar.com/2018-06/26/16/8fc8b7b4e79d5c81ffb04ae62a426108.jpg@!200w-c",
        "sale_price": "12.00",
        "market_price": "14.50",
        "youhui_price": "0.00",
        "fm_shareid": "0",
        "brandid": "122",
        "order": "900",
        "stockmode": "2",
        "replys": "7054",
        "asks": "198",
        "net_weight": "220.000",
        "nagpre": "0.02",
        "sold": "34927",
        "unit": "包",
        "isBest": "1",
        "stock": "1",
        "real_wid": "1",
        "href": "http://item.epet.com/112841.html"
    },
    {
        "gspid": "5900",
        "gid": "105900",
        "cateid": "4306",
        "subject": "爱丽思IRIS 牛奶味骨头型 饼干 500g",
        "presubject": "磨牙除口臭 健胃保健 强化钙质 有自封条",
        "formats": "",
        "formats_values": "[]",
        "photo": "//img1.epetbar.com/2015-11/25/16/16cb75fec2c7a7394731230b55e1b2d5.jpg@!200w-c",
        "sale_price": "21.00",
        "market_price": "33.00",
        "youhui_price": "0.00",
        "fm_shareid": "0",
        "brandid": "30",
        "order": "800",
        "stockmode": "2",
        "replys": "7837",
        "asks": "407",
        "net_weight": "500.000",
        "nagpre": "0.02",
        "sold": "38114",
        "unit": "袋",
        "isBest": "1",
        "stock": "1",
        "real_wid": "1",
        "href": "http://item.epet.com/105900.html"
    },
    {
        "gspid": "113228",
        "gid": "223386",
        "cateid": "4306",
        "subject": "阿飞和巴弟 钙奶小饼干成犬零食 270g",
        "presubject": "",
        "formats": "",
        "formats_values": "[]",
        "photo": "//img1.epetbar.com/2017-10/20/16/9b7118a53aa2df24690cdfc6a621b865.jpg@!200w-c",
        "sale_price": "19.90",
        "market_price": "39.80",
        "youhui_price": "0.00",
        "fm_shareid": "0",
        "brandid": "1622",
        "order": "800",
        "stockmode": "2",
        "replys": "535",
        "asks": "0",
        "net_weight": "270.000",
        "nagpre": "0.03",
        "sold": "1673",
        "unit": "罐",
        "isBest": "1",
        "stock": "1",
        "real_wid": "1",
        "href": "http://item.epet.com/223386.html"
    },
    {
        "gspid": "76277",
        "gid": "183549",
        "cateid": "4306",
        "subject": "K9 粗粮海星饼干狗零食 600g",
        "presubject": "健康粗粮 洁齿除口臭 促进食欲",
        "formats": " 海星饼干",
        "formats_values": "{\"7515\":12911}",
        "photo": "//img1.epetbar.com/2016-10/20/20/8390054890806c5a86ab534e65f2a165.jpg@!200w-c",
        "sale_price": "30.00",
        "market_price": "36.00",
        "youhui_price": "0.00",
        "fm_shareid": "183548",
        "brandid": "1441",
        "order": "700",
        "stockmode": "2",
        "replys": "527",
        "asks": "4",
        "net_weight": "600.000",
        "nagpre": "0.03",
        "sold": "921",
        "unit": "罐",
        "isBest": "1",
        "stock": "1",
        "real_wid": "1",
        "href": "http://item.epet.com/183549.html"
    },
    {
        "gspid": "11565",
        "gid": "111565",
        "cateid": "4306",
        "subject": "爱丽思IRIS 芝士小馒头 450g",
        "presubject": "促消化 降异味 润泽毛发",
        "formats": "",
        "formats_values": "[]",
        "photo": "//img1.epetbar.com/2014-12/04/ee721d747ed9bf5dbd87652a2ff873c7.jpg@!200w-c",
        "sale_price": "26.00",
        "market_price": "27.00",
        "youhui_price": "0.00",
        "fm_shareid": "111565",
        "brandid": "30",
        "order": "600",
        "stockmode": "2",
        "replys": "1269",
        "asks": "106",
        "net_weight": "500.000",
        "nagpre": "0.02",
        "sold": "6417",
        "unit": "袋",
        "isBest": "1",
        "stock": "1",
        "real_wid": "1",
        "href": "http://item.epet.com/111565.html"
    },
    {
        "gspid": "6158",
        "gid": "106158",
        "cateid": "4306",
        "subject": "哈格Hugdarling 米奇除臭小饼多味装100g ",
        "presubject": "洁齿除臭 多味享受 可爱米奇造型 新老包装随机发",
        "formats": "",
        "formats_values": "[]",
        "photo": "//img1.epetbar.com/2016-08/30/10/e358e1ee3c3e88440e539194fb80010a.jpg@!200w-c",
        "sale_price": "5.80",
        "market_price": "8.00",
        "youhui_price": "4.93",
        "fm_shareid": "106158",
        "brandid": "110",
        "order": "500",
        "stockmode": "2",
        "replys": "493",
        "asks": "11",
        "net_weight": "100.000",
        "nagpre": "0.06",
        "sold": "2257",
        "unit": "包",
        "isBest": "1",
        "stock": "1",
        "real_wid": "1",
        "href": "http://item.epet.com/106158.html"
    },
    {
        "gspid": "19571",
        "gid": "119632",
        "cateid": "4306",
        "subject": "宝路 成犬狗饼干 250g ",
        "presubject": "营养健康 均衡配比 口感极佳",
        "formats": "",
        "formats_values": "[]",
        "photo": "//img1.epetbar.com/2016-06/27/12/1ff6494147a1cb2bc2743187e458a396.jpg@!200w-c",
        "sale_price": "11.50",
        "market_price": "13.80",
        "youhui_price": "0.00",
        "fm_shareid": "119632",
        "brandid": "47",
        "order": "500",
        "stockmode": "2",
        "replys": "783",
        "asks": "30",
        "net_weight": "250.000",
        "nagpre": "0.04",
        "sold": "5268",
        "unit": "袋",
        "isBest": "1",
        "stock": "1",
        "real_wid": "1",
        "href": "http://item.epet.com/119632.html"
    },
    {
        "gspid": "76276",
        "gid": "183548",
        "cateid": "4306",
        "subject": "K9 圆形曲奇洁齿猴菇饼干狗粮食 600g",
        "presubject": "健康粗粮 洁齿除口臭 促进食欲",
        "formats": " 曲奇饼干",
        "formats_values": "{\"7515\":18059}",
        "photo": "//img1.epetbar.com/2016-10/20/20/8fb5b2bbab782c051a3fdaf52357f59c.jpg@!200w-c",
        "sale_price": "30.00",
        "market_price": "36.00",
        "youhui_price": "0.00",
        "fm_shareid": "183548",
        "brandid": "1441",
        "order": "500",
        "stockmode": "2",
        "replys": "527",
        "asks": "4",
        "net_weight": "600.000",
        "nagpre": "0.02",
        "sold": "514",
        "unit": "罐",
        "isBest": "1",
        "stock": "1",
        "real_wid": "1",
        "href": "http://item.epet.com/183548.html"
    },
    {
        "gspid": "77207",
        "gid": "184563",
        "cateid": "4308",
        "subject": "新西兰原装进口K9Natural 佐餐系列 牛肉冻干犬佐餐 142g",
        "presubject": " 天然无谷 易消化护关节 90%以上肉含量 高适口性",
        "formats": " 牛肉",
        "formats_values": "{\"7515\":7581}",
        "photo": "//img1.epetbar.com/2016-10/18/16/ad438029c2f638328816bd7f30be48bc.jpg@!200w-c",
        "sale_price": "138.00",
        "market_price": "165.60",
        "youhui_price": "0.00",
        "fm_shareid": "174075",
        "brandid": "495",
        "order": "0",
        "stockmode": "2",
        "replys": "263",
        "asks": "28",
        "net_weight": "142.000",
        "nagpre": "0.02",
        "sold": "427",
        "unit": "袋",
        "isBest": "1",
        "stock": "1",
        "real_wid": "1",
        "href": "http://item.epet.com/184563.html"
    },
    {
        "gspid": "84694",
        "gid": "192477",
        "cateid": "4308",
        "subject": "嗗达Woofstard 天然鸡肉冻干零食 100g",
        "presubject": "真空脱水工艺 纯鲜肉制作 最大程度保留营养 无添加剂、防腐及色素",
        "formats": " 鸡肉",
        "formats_values": "{\"7515\":7579}",
        "photo": "//img1.epetbar.com/2017-02/13/14/74ec3932bdeb3c1d7092da81173127b9.png@!200w-c",
        "sale_price": "35.00",
        "market_price": "48.00",
        "youhui_price": "0.00",
        "fm_shareid": "192481",
        "brandid": "1205",
        "order": "0",
        "stockmode": "2",
        "replys": "592",
        "asks": "7",
        "net_weight": "100.000",
        "nagpre": "0.04",
        "sold": "922",
        "unit": "袋",
        "isBest": "1",
        "stock": "1",
        "real_wid": "1",
        "href": "http://item.epet.com/192477.html"
    },
    {
        "gspid": "84695",
        "gid": "192478",
        "cateid": "4308",
        "subject": "嗗达Woofstard 天然鸭肉冻干零食 100g",
        "presubject": "真空脱水工艺 纯鲜肉制作 最大程度保留营养 无添加剂、防腐及色素",
        "formats": " 鸭肉",
        "formats_values": "{\"7515\":7661}",
        "photo": "//img1.epetbar.com/2017-02/13/14/538afa1e3c8f5d99ee7286374b7781b2.png@!200w-c",
        "sale_price": "35.00",
        "market_price": "48.00",
        "youhui_price": "0.00",
        "fm_shareid": "192481",
        "brandid": "1205",
        "order": "0",
        "stockmode": "2",
        "replys": "592",
        "asks": "7",
        "net_weight": "100.000",
        "nagpre": "0.01",
        "sold": "1037",
        "unit": "袋",
        "isBest": "1",
        "stock": "1",
        "real_wid": "1",
        "href": "http://item.epet.com/192478.html"
    },
    {
        "gspid": "84696",
        "gid": "192479",
        "cateid": "4308",
        "subject": "嗗达Woofstard 天然三文鱼冻干零食 100g",
        "presubject": "真空脱水工艺 纯鲜肉制作 最大程度保留营养 无添加剂、防腐及色素",
        "formats": " 三文鱼",
        "formats_values": "{\"7515\":7651}",
        "photo": "//img1.epetbar.com/2017-02/13/14/1aaf055ac596da238e13f6a08163691f.png@!200w-c",
        "sale_price": "46.00",
        "market_price": "59.00",
        "youhui_price": "0.00",
        "fm_shareid": "192481",
        "brandid": "1205",
        "order": "0",
        "stockmode": "2",
        "replys": "592",
        "asks": "7",
        "net_weight": "100.000",
        "nagpre": "0.01",
        "sold": "398",
        "unit": "袋",
        "isBest": "1",
        "stock": "1",
        "real_wid": "1",
        "href": "http://item.epet.com/192479.html"
    },
    {
        "gspid": "84697",
        "gid": "192480",
        "cateid": "4308",
        "subject": "嗗达Woofstard 天然鳕鱼冻干零食 100g",
        "presubject": "真空脱水工艺 纯鲜肉制作 最大程度保留营养 无添加剂、防腐及色素",
        "formats": " 鳕鱼",
        "formats_values": "{\"7515\":9130}",
        "photo": "//img1.epetbar.com/2017-02/13/14/288d58d3a0dcf99d28528b9ea3ed7bbc.png@!200w-c",
        "sale_price": "49.00",
        "market_price": "59.00",
        "youhui_price": "0.00",
        "fm_shareid": "192481",
        "brandid": "1205",
        "order": "0",
        "stockmode": "2",
        "replys": "592",
        "asks": "7",
        "net_weight": "100.000",
        "nagpre": "0.02",
        "sold": "238",
        "unit": "袋",
        "isBest": "1",
        "stock": "1",
        "real_wid": "1",
        "href": "http://item.epet.com/192480.html"
    },
    {
        "gspid": "92575",
        "gid": "200731",
        "cateid": "4308",
        "subject": "TOMI 冻干鸡肉犬零食 55g",
        "presubject": "纯肉入料 高蛋白看得见原料的脱水零食",
        "formats": " 鸡肉",
        "formats_values": "{\"7515\":7579}",
        "photo": "//img1.epetbar.com/2017-06/05/16/fe01d82640a766b2bb94ccd97680eb0d.jpg@!200w-c",
        "sale_price": "38.00",
        "market_price": "42.00",
        "youhui_price": "0.00",
        "fm_shareid": "200734",
        "brandid": "1559",
        "order": "0",
        "stockmode": "2",
        "replys": "123",
        "asks": "0",
        "net_weight": "55.000",
        "nagpre": "0.00",
        "sold": "29",
        "unit": "盒",
        "isBest": "1",
        "stock": "1",
        "real_wid": "1",
        "href": "http://item.epet.com/200731.html"
    },
    {
        "gspid": "92585",
        "gid": "200741",
        "cateid": "4308",
        "subject": "SALMON4PETS 冻干渔夫雪茄狗零食 70g",
        "presubject": "冷冻干 海洋野生鱼 营养美味",
        "formats": "",
        "formats_values": "[]",
        "photo": "//img1.epetbar.com/2017-06/23/10/b903c9639d2dd0ac8f8da324f3eb9e53.jpg@!200w-c",
        "sale_price": "43.00",
        "market_price": "55.90",
        "youhui_price": "0.00",
        "fm_shareid": "0",
        "brandid": "1557",
        "order": "0",
        "stockmode": "2",
        "replys": "12",
        "asks": "0",
        "net_weight": "70.000",
        "nagpre": "0.00",
        "sold": "27",
        "unit": "袋",
        "isBest": "1",
        "stock": "1",
        "real_wid": "1",
        "href": "http://item.epet.com/200741.html"
    },
    {
        "gspid": "92587",
        "gid": "200743",
        "cateid": "4308",
        "subject": "SALMON4PETS 冻干三文鱼鱼皮绕方棒狗零食 70g",
        "presubject": "冷冻干 野生三文鱼 营养美味",
        "formats": "",
        "formats_values": "[]",
        "photo": "//img1.epetbar.com/2017-06/23/10/d03c9ef43ae74912eedc4e3cdaa7dff9.jpg@!200w-c",
        "sale_price": "38.00",
        "market_price": "49.40",
        "youhui_price": "0.00",
        "fm_shareid": "0",
        "brandid": "1557",
        "order": "0",
        "stockmode": "2",
        "replys": "9",
        "asks": "0",
        "net_weight": "70.000",
        "nagpre": "0.00",
        "sold": "27",
        "unit": "袋",
        "isBest": "1",
        "stock": "1",
        "real_wid": "1",
        "href": "http://item.epet.com/200743.html"
    }
]